{
  "meta": {
    "sp": {
      "count": 23,
      "entityLevel": "adGroup",
      "sampleKeys": [
        "ACOS",
        "CPC",
        "CPS",
        "CTR",
        "Clicks",
        "ConversionRate",
        "Impressions",
        "Orders",
        "ROAS",
        "SPS",
        "Sales",
        "SalesOtherSku7d",
        "SalesSameSku7d",
        "Spend",
        "UnitsSoldOtherSku7d",
        "UnitsSoldSameSku7d",
        "accountId",
        "acos_15",
        "acos_30",
        "acos_7",
        "acos_life_time",
        "adGroupId",
        "adId",
        "asin",
        "campaignId",
        "campaignName",
        "campaignState",
        "created_at",
        "dailyBudget",
        "groupName",
        "groupState",
        "hasPlacement",
        "isPublic",
        "keywordPosition",
        "lastAdvUpdatedDate",
        "lowCost",
        "manualAdjustTheTime",
        "memoKey",
        "moduleId",
        "moduleName",
        "placementACOSMin",
        "positionType",
        "productLine",
        "productVariantInfo",
        "proportion",
        "servingStatus",
        "servingStatusDetail",
        "servingStatusTitle",
        "siteId",
        "sku",
        "skuInvData",
        "startDate",
        "state",
        "test_module",
        "updateWeekday"
      ],
      "sample": {
        "ACOS": null,
        "CPC": "0.364285",
        "CPS": null,
        "CTR": "0.009162303664921465",
        "Clicks": "14",
        "ConversionRate": "0",
        "Impressions": "1528",
        "Orders": "0",
        "ROAS": "0.000000",
        "SPS": null,
        "Sales": "0.00",
        "SalesOtherSku7d": "0.00",
        "SalesSameSku7d": "0.00",
        "Spend": "5.10",
        "UnitsSoldOtherSku7d": "0",
        "UnitsSoldSameSku7d": "0",
        "accountId": 120,
        "acos_15": null,
        "acos_30": null,
        "acos_7": null,
        "acos_life_time": "0.186331",
        "adGroupId": 335413796452031,
        "adId": 298336744510492,
        "asin": "B0CLV16D1L",
        "campaignId": 396698961698398,
        "campaignName": "auto_silicone cable ties_th2843",
        "campaignState": 1,
        "created_at": "2025-05-06 17:46:19",
        "dailyBudget": "3.00",
        "groupName": "auto_silicone cable ties_th2843"
      }
    },
    "sb": {
      "count": 0,
      "entityLevel": "campaign",
      "sampleKeys": [],
      "sample": null
    }
  },
  "spRows": [
    {
      "ACOS": null,
      "CPC": "0.364285",
      "CPS": null,
      "CTR": "0.009162303664921465",
      "Clicks": "14",
      "ConversionRate": "0",
      "Impressions": "1528",
      "Orders": "0",
      "ROAS": "0.000000",
      "SPS": null,
      "Sales": "0.00",
      "SalesOtherSku7d": "0.00",
      "SalesSameSku7d": "0.00",
      "Spend": "5.10",
      "UnitsSoldOtherSku7d": "0",
      "UnitsSoldSameSku7d": "0",
      "accountId": 120,
      "acos_15": null,
      "acos_30": null,
      "acos_7": null,
      "acos_life_time": "0.186331",
      "adGroupId": 335413796452031,
      "adId": 298336744510492,
      "asin": "B0CLV16D1L",
      "campaignId": 396698961698398,
      "campaignName": "auto_silicone cable ties_th2843",
      "campaignState": 1,
      "created_at": "2025-05-06 17:46:19",
      "dailyBudget": "3.00",
      "groupName": "auto_silicone cable ties_th2843",
      "groupState": 1,
      "hasPlacement": 0,
      "isPublic": false,
      "keywordPosition": 0,
      "lastAdvUpdatedDate": "2026-04-10 18:50:31",
      "lowCost": 0,
      "manualAdjustTheTime": "2026-04-16 22:08:41",
      "memoKey": null,
      "moduleId": 0,
      "moduleName": "",
      "placementACOSMin": null,
      "positionType": "auto",
      "productLine": {
        "cpc": "0.884494",
        "cps": "5.086252354048964",
        "ctr": "0.65",
        "sku": "TH2843"
      },
      "productVariantInfo": {
        "asin": "B0CLV16D1L",
        "productType": "变体",
        "sku": "TH2843",
        "variantData": {
          "COLOR": "Gray",
          "SIZE": "7.1 Inch"
        },
        "variationThemeName": "SIZE/COLOR"
      },
      "proportion": 0,
      "servingStatus": "AD_STATUS_LIVE",
      "servingStatusDetail": "",
      "servingStatusTitle": "ELIGIBLE;",
      "siteId": 4,
      "sku": "TH2843",
      "skuInvData": {
        "asin": "B0CLV16D1L",
        "ful_date": "2023-11-04",
        "graphics_url": "https://m.media-amazon.com/images/I/41rDn8YIjfL._SL75_.jpg",
        "price": "17.99",
        "sale_status": "正常销售",
        "sales_day": "18 / 42 / 26",
        "servingStatusDetail": "",
        "servingStatusTitle": "ELIGIBLE;",
        "sku": "TH2843",
        "solr_term": "常规产品"
      },
      "startDate": "2025-05-06",
      "state": 1,
      "test_module": [],
      "updateWeekday": "否"
    },
    {
      "ACOS": null,
      "CPC": null,
      "CPS": null,
      "CTR": "0",
      "Clicks": "0",
      "ConversionRate": null,
      "Impressions": "28",
      "Orders": "0",
      "ROAS": null,
      "SPS": null,
      "Sales": "0.00",
      "SalesOtherSku7d": "0.00",
      "SalesSameSku7d": "0.00",
      "Spend": "0.00",
      "UnitsSoldOtherSku7d": "0",
      "UnitsSoldSameSku7d": "0",
      "accountId": 423,
      "acos_15": null,
      "acos_30": null,
      "acos_7": null,
      "acos_life_time": "0.366839",
      "adGroupId": 462820465028833,
      "adId": 439507623956698,
      "asin": "B0C4F49DT9",
      "campaignId": 268439054249692,
      "campaignName": "auto_baby shower games boy_yan2278",
      "campaignState": 1,
      "created_at": "2026-01-23 18:08:16",
      "dailyBudget": "3.00",
      "groupName": "auto_baby shower games boy_yan2278",
      "groupState": 1,
      "hasPlacement": 0,
      "isPublic": false,
      "keywordPosition": 1,
      "lastAdvUpdatedDate": "2026-04-10 10:37:44",
      "lowCost": 0,
      "manualAdjustTheTime": "2026-04-16 21:54:16",
      "memoKey": null,
      "moduleId": 0,
      "moduleName": "",
      "placementACOSMin": null,
      "positionType": "auto",
      "productLine": {
        "cpc": "0.326250",
        "cps": "11.393042190969652",
        "ctr": "1.29",
        "sku": "YAN2278"
      },
      "productVariantInfo": {
        "asin": "B0C4F49DT9",
        "productType": "组合变体",
        "sku": "YAN2278",
        "variantData": {
          "COLOR_NAME": "Blue",
          "STYLE_NAME": "Bear"
        },
        "variationThemeName": "COLOR_NAME/STYLE_NAME"
      },
      "proportion": 0,
      "servingStatus": "AD_STATUS_LIVE",
      "servingStatusDetail": "",
      "servingStatusTitle": "ELIGIBLE;",
      "siteId": 4,
      "sku": "YAN2278",
      "skuInvData": {
        "asin": "B0C4F49DT9",
        "ful_date": "2023-05-18",
        "graphics_url": "https://m.media-amazon.com/images/I/51QBkkfSr7L._SL75_.jpg",
        "price": "9.99",
        "sale_status": "正常销售",
        "sales_day": "86 / 64 / 61",
        "servingStatusDetail": "",
        "servingStatusTitle": "ELIGIBLE;",
        "sku": "YAN2278",
        "solr_term": "夏季产品(平时可卖)"
      },
      "startDate": "2026-01-23",
      "state": 1,
      "test_module": [],
      "updateWeekday": "否"
    },
    {
      "ACOS": null,
      "CPC": null,
      "CPS": null,
      "CTR": "0",
      "Clicks": "0",
      "ConversionRate": null,
      "Impressions": "24",
      "Orders": "0",
      "ROAS": null,
      "SPS": null,
      "Sales": "0.00",
      "SalesOtherSku7d": "0.00",
      "SalesSameSku7d": "0.00",
      "Spend": "0.00",
      "UnitsSoldOtherSku7d": "0",
      "UnitsSoldSameSku7d": "0",
      "accountId": 639,
      "acos_15": null,
      "acos_30": null,
      "acos_7": null,
      "acos_life_time": null,
      "adGroupId": 93748062162119,
      "adId": 549164375453880,
      "asin": "B0CH8RJFTG",
      "campaignId": 43389552451606,
      "campaignName": "kw broad_easter bread basket_dun1150",
      "campaignState": 1,
      "created_at": "2026-03-25 18:35:00",
      "dailyBudget": "3.00",
      "groupName": "kw broad_easter bread basket_dun1150",
      "groupState": 1,
      "hasPlacement": 0,
      "isPublic": false,
      "keywordPosition": 1,
      "lastAdvUpdatedDate": "2026-04-08 10:23:16",
      "lowCost": 0,
      "manualAdjustTheTime": "2026-04-08 10:23:16",
      "memoKey": null,
      "moduleId": 0,
      "moduleName": "",
      "placementACOSMin": null,
      "positionType": "keywordTarget",
      "productLine": {
        "cpc": "0.503029",
        "cps": "16.93148880105402",
        "ctr": "0.8",
        "sku": "DUN1150"
      },
      "productVariantInfo": {
        "asin": "B0CH8RJFTG",
        "productType": "变体",
        "sku": "DUN1150",
        "variantData": "",
        "variationThemeName": ""
      },
      "proportion": 0,
      "servingStatus": "AD_STATUS_LIVE",
      "servingStatusDetail": "",
      "servingStatusTitle": "ELIGIBLE;",
      "siteId": 4,
      "sku": "DUN1150",
      "skuInvData": {
        "asin": "B0CH8RJFTG",
        "ful_date": "2023-10-25",
        "graphics_url": "https://m.media-amazon.com/images/I/512Sbatg49L._SL75_.jpg",
        "price": "41.99",
        "sale_status": "正常销售",
        "sales_day": "999 / 999 / 44",
        "servingStatusDetail": "",
        "servingStatusTitle": "ELIGIBLE;",
        "sku": "DUN1150",
        "solr_term": "感恩节(平时可卖)"
      },
      "startDate": "2026-03-25",
      "state": 1,
      "test_module": [],
      "updateWeekday": "否"
    },
    {
      "ACOS": null,
      "CPC": null,
      "CPS": null,
      "CTR": null,
      "Clicks": null,
      "ConversionRate": null,
      "Impressions": null,
      "Orders": null,
      "ROAS": null,
      "SPS": null,
      "Sales": null,
      "SalesOtherSku7d": null,
      "SalesSameSku7d": null,
      "Spend": null,
      "UnitsSoldOtherSku7d": null,
      "UnitsSoldSameSku7d": null,
      "accountId": 294,
      "acos_15": null,
      "acos_30": null,
      "acos_7": null,
      "acos_life_time": "0.111346",
      "adGroupId": 427534554674792,
      "adId": 494490211455532,
      "asin": "B0DW931ZLZ",
      "campaignId": 547909368577983,
      "campaignName": "auto_christian gifts for women_zo0892",
      "campaignState": 1,
      "created_at": "2025-03-13 08:34:16",
      "dailyBudget": "30.00",
      "groupName": "christian gifts for women-zo0892-system-a",
      "groupState": 1,
      "hasPlacement": 0,
      "isPublic": false,
      "keywordPosition": 1,
      "lastAdvUpdatedDate": "2026-03-25 23:26:30",
      "lowCost": 0,
      "manualAdjustTheTime": "2026-03-25 23:26:30",
      "memoKey": null,
      "moduleId": 0,
      "moduleName": "",
      "placementACOSMin": null,
      "positionType": "auto",
      "productLine": {
        "cpc": "0.294032",
        "cps": "21.127161055505006",
        "ctr": "1.46",
        "sku": "ZO0892"
      },
      "productVariantInfo": {
        "asin": "B0DW931ZLZ",
        "productType": "变体",
        "sku": "ZO0892",
        "variantData": {
          "ITEM_PACKAGE_QUANTITY": "12 Pcs"
        },
        "variationThemeName": "ITEM_PACKAGE_QUANTITY"
      },
      "proportion": 0,
      "servingStatus": "AD_STATUS_LIVE",
      "servingStatusDetail": "",
      "servingStatusTitle": "ELIGIBLE;",
      "siteId": 4,
      "sku": "ZO0892",
      "skuInvData": {
        "asin": "B0DW931ZLZ",
        "ful_date": "2025-03-13",
        "graphics_url": "https://m.media-amazon.com/images/I/51lCqPzan1L._SL75_.jpg",
        "price": "45.99",
        "sale_status": "正常销售",
        "sales_day": "999 / 199 / 365",
        "servingStatusDetail": "",
        "servingStatusTitle": "ELIGIBLE;",
        "sku": "ZO0892",
        "solr_term": "夏季产品(平时可卖)"
      },
      "startDate": "2025-03-13",
      "state": 1,
      "test_module": [],
      "updateWeekday": "否"
    },
    {
      "ACOS": null,
      "CPC": null,
      "CPS": null,
      "CTR": null,
      "Clicks": null,
      "ConversionRate": null,
      "Impressions": null,
      "Orders": null,
      "ROAS": null,
      "SPS": null,
      "Sales": null,
      "SalesOtherSku7d": null,
      "SalesSameSku7d": null,
      "Spend": null,
      "UnitsSoldOtherSku7d": null,
      "UnitsSoldSameSku7d": null,
      "accountId": 294,
      "acos_15": null,
      "acos_30": null,
      "acos_7": null,
      "acos_life_time": null,
      "adGroupId": 546789717653709,
      "adId": 493702707084103,
      "asin": "B0DW8ZQX13",
      "campaignId": 284834511029071,
      "campaignName": "christian gifts for women-zo0892-system-keyword",
      "campaignState": 1,
      "created_at": "2025-06-12 19:50:35",
      "dailyBudget": "3.00",
      "groupName": "core",
      "groupState": 1,
      "hasPlacement": 0,
      "isPublic": false,
      "keywordPosition": 1,
      "lastAdvUpdatedDate": "2026-03-25 23:26:47",
      "lowCost": 0,
      "manualAdjustTheTime": "2026-04-10 13:02:33",
      "memoKey": null,
      "moduleId": 0,
      "moduleName": "",
      "placementACOSMin": null,
      "positionType": "keywordTarget",
      "productLine": {
        "cpc": "0.294032",
        "cps": "21.127161055505006",
        "ctr": "1.46",
        "sku": "ZO0891"
      },
      "productVariantInfo": {
        "asin": "B0DW8ZQX13",
        "productType": "普通产品",
        "sku": "ZO0891",
        "variantData": {
          "ITEM_PACKAGE_QUANTITY": "6 Pcs"
        },
        "variationThemeName": "ITEM_PACKAGE_QUANTITY"
      },
      "proportion": 0,
      "servingStatus": "AD_STATUS_LIVE",
      "servingStatusDetail": "",
      "servingStatusTitle": "ELIGIBLE;",
      "siteId": 4,
      "sku": "ZO0891",
      "skuInvData": {
        "asin": "B0DW8ZQX13",
        "ful_date": "2025-03-13",
        "graphics_url": "https://m.media-amazon.com/images/I/51-KP0PdMXL._SL75_.jpg",
        "price": "26.99",
        "sale_status": "正常销售",
        "sales_day": "141 / 329 / 1410",
        "servingStatusDetail": "",
        "servingStatusTitle": "ELIGIBLE;",
        "sku": "ZO0891",
        "solr_term": "夏季产品(平时可卖)"
      },
      "startDate": "2025-06-12",
      "state": 1,
      "test_module": [],
      "updateWeekday": "否"
    },
    {
      "ACOS": null,
      "CPC": null,
      "CPS": null,
      "CTR": null,
      "Clicks": null,
      "ConversionRate": null,
      "Impressions": null,
      "Orders": null,
      "ROAS": null,
      "SPS": null,
      "Sales": null,
      "SalesOtherSku7d": null,
      "SalesSameSku7d": null,
      "Spend": null,
      "UnitsSoldOtherSku7d": null,
      "UnitsSoldSameSku7d": null,
      "accountId": 752,
      "acos_15": null,
      "acos_30": null,
      "acos_7": null,
      "acos_life_time": "0.163403",
      "adGroupId": 341551208532334,
      "adId": 466042878549048,
      "asin": "B0DLWFLBDJ",
      "campaignId": 481583699624095,
      "campaignName": "asin_ballpoint pen_nay0963",
      "campaignState": 1,
      "created_at": "2025-01-08 17:41:46",
      "dailyBudget": "3.00",
      "groupName": "asin_ballpoint pen_nay0963",
      "groupState": 1,
      "hasPlacement": 0,
      "isPublic": false,
      "keywordPosition": 1,
      "lastAdvUpdatedDate": "2026-03-25 23:26:15",
      "lowCost": 0,
      "manualAdjustTheTime": "2026-03-25 23:26:15",
      "memoKey": null,
      "moduleId": 0,
      "moduleName": "",
      "placementACOSMin": null,
      "positionType": "productTarget",
      "productLine": {
        "cpc": "0.286888",
        "cps": "15.706558996107594",
        "ctr": "1.23",
        "sku": "NAY0963"
      },
      "productVariantInfo": {
        "asin": "B0DLWFLBDJ",
        "productType": "组合变体",
        "sku": "NAY0963",
        "variantData": {
          "ITEM_PACKAGE_QUANTITY": "25 Set",
          "STYLE_NAME": "Botanical"
        },
        "variationThemeName": "ITEM_PACKAGE_QUANTITY/STYLE_NAME"
      },
      "proportion": 0,
      "servingStatus": "AD_STATUS_LIVE",
      "servingStatusDetail": "",
      "servingStatusTitle": "ELIGIBLE;",
      "siteId": 4,
      "sku": "NAY0963",
      "skuInvData": {
        "asin": "B0DLWFLBDJ",
        "ful_date": "2024-12-29",
        "graphics_url": "https://m.media-amazon.com/images/I/51vqiMTHagL._SL75_.jpg",
        "price": "19.99",
        "sale_status": "正常销售",
        "sales_day": "15 / 30 / 47",
        "servingStatusDetail": "",
        "servingStatusTitle": "ELIGIBLE;",
        "sku": "NAY0963",
        "solr_term": "婚礼季(平时可卖)"
      },
      "startDate": "2025-01-08",
      "state": 1,
      "test_module": [],
      "updateWeekday": "否"
    },
    {
      "ACOS": null,
      "CPC": null,
      "CPS": null,
      "CTR": null,
      "Clicks": null,
      "ConversionRate": null,
      "Impressions": null,
      "Orders": null,
      "ROAS": null,
      "SPS": null,
      "Sales": null,
      "SalesOtherSku7d": null,
      "SalesSameSku7d": null,
      "Spend": null,
      "UnitsSoldOtherSku7d": null,
      "UnitsSoldSameSku7d": null,
      "accountId": 388,
      "acos_15": null,
      "acos_30": null,
      "acos_7": null,
      "acos_life_time": "0.276985",
      "adGroupId": 330045573319481,
      "adId": 439705435364575,
      "asin": "B0F2F7NBYR",
      "campaignId": 447627255152480,
      "campaignName": "kw_blue floralbags_qa3896",
      "campaignState": 1,
      "created_at": "2025-05-07 17:32:01",
      "dailyBudget": "7.00",
      "groupName": "kw_blue floralbags_qa3896",
      "groupState": 1,
      "hasPlacement": 0,
      "isPublic": false,
      "keywordPosition": 1,
      "lastAdvUpdatedDate": "2026-03-30 17:47:04",
      "lowCost": 0,
      "manualAdjustTheTime": "2026-03-30 17:47:04",
      "memoKey": null,
      "moduleId": 0,
      "moduleName": "",
      "placementACOSMin": null,
      "positionType": "keywordTarget",
      "productLine": {
        "cpc": "0.312669",
        "cps": "19.369356486210418",
        "ctr": "1.44",
        "sku": "QA3896"
      },
      "productVariantInfo": {
        "asin": "B0F2F7NBYR",
        "productType": "组合产品",
        "sku": "QA3896",
        "variantData": "",
        "variationThemeName": ""
      },
      "proportion": 0,
      "servingStatus": "AD_STATUS_LIVE",
      "servingStatusDetail": "",
      "servingStatusTitle": "ELIGIBLE;",
      "siteId": 4,
      "sku": "QA3896",
      "skuInvData": {
        "asin": "B0F2F7NBYR",
        "ful_date": "2025-04-29",
        "graphics_url": "https://m.media-amazon.com/images/I/51e38f31ewL._SL75_.jpg",
        "price": "29.99",
        "sale_status": "正常销售",
        "sales_day": "999 / 122 / 312",
        "servingStatusDetail": "",
        "servingStatusTitle": "ELIGIBLE;",
        "sku": "QA3896",
        "solr_term": "婚礼季(平时可卖)"
      },
      "startDate": "2025-05-07",
      "state": 1,
      "test_module": [],
      "updateWeekday": "否"
    },
    {
      "ACOS": null,
      "CPC": null,
      "CPS": null,
      "CTR": null,
      "Clicks": null,
      "ConversionRate": null,
      "Impressions": null,
      "Orders": null,
      "ROAS": null,
      "SPS": null,
      "Sales": null,
      "SalesOtherSku7d": null,
      "SalesSameSku7d": null,
      "Spend": null,
      "UnitsSoldOtherSku7d": null,
      "UnitsSoldSameSku7d": null,
      "accountId": 423,
      "acos_15": null,
      "acos_30": null,
      "acos_7": null,
      "acos_life_time": "0.219944",
      "adGroupId": 492374673770606,
      "adId": 391031115887955,
      "asin": "B0BPFTLP8S",
      "campaignId": 385123769483270,
      "campaignName": "kw_tieshoe_yan1353-2008",
      "campaignState": 1,
      "created_at": "2024-11-13 18:52:07",
      "dailyBudget": "3.00",
      "groupName": "kw_core",
      "groupState": 1,
      "hasPlacement": 0,
      "isPublic": false,
      "keywordPosition": 0,
      "lastAdvUpdatedDate": "2026-02-24 09:38:32",
      "lowCost": 0,
      "manualAdjustTheTime": "2026-02-24 09:38:32",
      "memoKey": null,
      "moduleId": 0,
      "moduleName": "",
      "placementACOSMin": null,
      "positionType": "keywordTarget",
      "productLine": {
        "cpc": "0.295997",
        "cps": "11.457387048971293",
        "ctr": "1.13",
        "sku": "YAN1353"
      },
      "productVariantInfo": {
        "asin": "B0BPFTLP8S",
        "productType": "组合产品",
        "sku": "YAN1353",
        "variantData": {
          "COLOR_NAME": "Pink",
          "STYLE_NAME": "Leaf"
        },
        "variationThemeName": "COLOR_NAME/STYLE_NAME"
      },
      "proportion": 0,
      "servingStatus": "AD_STATUS_LIVE",
      "servingStatusDetail": "",
      "servingStatusTitle": "ELIGIBLE;",
      "siteId": 4,
      "sku": "YAN1353",
      "skuInvData": {
        "asin": "B0BPFTLP8S",
        "ful_date": "2023-02-03",
        "graphics_url": "https://m.media-amazon.com/images/I/51uHV3GU-3L._SL75_.jpg",
        "price": "9.99",
        "sale_status": "正常销售",
        "sales_day": "90 / 158 / 169",
        "servingStatusDetail": "",
        "servingStatusTitle": "ELIGIBLE;",
        "sku": "YAN1353",
        "solr_term": "夏季产品(平时可卖)"
      },
      "startDate": "2024-11-13",
      "state": 1,
      "test_module": [],
      "updateWeekday": "否"
    },
    {
      "ACOS": null,
      "CPC": null,
      "CPS": null,
      "CTR": null,
      "Clicks": null,
      "ConversionRate": null,
      "Impressions": null,
      "Orders": null,
      "ROAS": null,
      "SPS": null,
      "Sales": null,
      "SalesOtherSku7d": null,
      "SalesSameSku7d": null,
      "Spend": null,
      "UnitsSoldOtherSku7d": null,
      "UnitsSoldSameSku7d": null,
      "accountId": 256,
      "acos_15": null,
      "acos_30": null,
      "acos_7": null,
      "acos_life_time": "0.226743",
      "adGroupId": 557772063447648,
      "adId": 537938680450998,
      "asin": "B09Q8G7Q9P",
      "campaignId": 465131688062269,
      "campaignName": "asin_photocard_oc1858",
      "campaignState": 1,
      "created_at": "2024-12-13 12:05:29",
      "dailyBudget": "3.00",
      "groupName": "asin_photocard_oc1858",
      "groupState": 1,
      "hasPlacement": 0,
      "isPublic": false,
      "keywordPosition": 1,
      "lastAdvUpdatedDate": "2026-03-30 17:11:32",
      "lowCost": 0,
      "manualAdjustTheTime": "2026-03-30 17:11:32",
      "memoKey": null,
      "moduleId": 0,
      "moduleName": "",
      "placementACOSMin": null,
      "positionType": "productTarget",
      "productLine": {
        "cpc": "0.371957",
        "cps": "14.861080485115766",
        "ctr": "1.03",
        "sku": "OC1858"
      },
      "productVariantInfo": {
        "asin": "B09Q8G7Q9P",
        "productType": "组合产品",
        "sku": "OC1858",
        "variantData": "",
        "variationThemeName": ""
      },
      "proportion": 0,
      "servingStatus": "AD_STATUS_LIVE",
      "servingStatusDetail": "",
      "servingStatusTitle": "ELIGIBLE;",
      "siteId": 4,
      "sku": "OC1858",
      "skuInvData": {
        "asin": "B09Q8G7Q9P",
        "ful_date": "2022-01-28",
        "graphics_url": "https://m.media-amazon.com/images/I/510oAJz3VML._SL75_.jpg",
        "price": "9.99",
        "sale_status": "正常销售",
        "sales_day": "120 / 186 / 150",
        "servingStatusDetail": "",
        "servingStatusTitle": "ELIGIBLE;",
        "sku": "OC1858",
        "solr_term": "常规产品"
      },
      "startDate": "2024-12-13",
      "state": 1,
      "test_module": [],
      "updateWeekday": "否"
    },
    {
      "ACOS": null,
      "CPC": null,
      "CPS": null,
      "CTR": null,
      "Clicks": null,
      "ConversionRate": null,
      "Impressions": null,
      "Orders": null,
      "ROAS": null,
      "SPS": null,
      "Sales": null,
      "SalesOtherSku7d": null,
      "SalesSameSku7d": null,
      "Spend": null,
      "UnitsSoldOtherSku7d": null,
      "UnitsSoldSameSku7d": null,
      "accountId": 423,
      "acos_15": null,
      "acos_30": null,
      "acos_7": null,
      "acos_life_time": "0.425959",
      "adGroupId": 337378426796062,
      "adId": 284585820123346,
      "asin": "B0BC8FT8MJ",
      "campaignId": 495673565134857,
      "campaignName": "kw_cardinal memorial_yan0087",
      "campaignState": 1,
      "created_at": "2025-04-14 11:12:21",
      "dailyBudget": "6.00",
      "groupName": "kw_cardinal memorial_yan0087",
      "groupState": 1,
      "hasPlacement": 0,
      "isPublic": false,
      "keywordPosition": 1,
      "lastAdvUpdatedDate": "2026-03-26 18:48:48",
      "lowCost": 0,
      "manualAdjustTheTime": "2026-03-26 18:48:48",
      "memoKey": null,
      "moduleId": 0,
      "moduleName": "",
      "placementACOSMin": null,
      "positionType": "keywordTarget",
      "productLine": {
        "cpc": "0.369394",
        "cps": "18.491522265697782",
        "ctr": "1.27",
        "sku": "YAN0087"
      },
      "productVariantInfo": {
        "asin": "B0BC8FT8MJ",
        "productType": "普通产品",
        "sku": "YAN0087",
        "variantData": "",
        "variationThemeName": ""
      },
      "proportion": 0,
      "servingStatus": "AD_STATUS_LIVE",
      "servingStatusDetail": "",
      "servingStatusTitle": "ELIGIBLE;",
      "siteId": 4,
      "sku": "YAN0087",
      "skuInvData": {
        "asin": "B0BC8FT8MJ",
        "ful_date": "2022-11-04",
        "graphics_url": "https://m.media-amazon.com/images/I/51u8o1w7emL._SL75_.jpg",
        "price": "11.99",
        "sale_status": "正常销售",
        "sales_day": "381 / 99 / 83",
        "servingStatusDetail": "",
        "servingStatusTitle": "ELIGIBLE;",
        "sku": "YAN0087",
        "solr_term": "圣诞节(平时可卖)"
      },
      "startDate": "2025-04-14",
      "state": 1,
      "test_module": [],
      "updateWeekday": "否"
    },
    {
      "ACOS": null,
      "CPC": null,
      "CPS": null,
      "CTR": null,
      "Clicks": null,
      "ConversionRate": null,
      "Impressions": null,
      "Orders": null,
      "ROAS": null,
      "SPS": null,
      "Sales": null,
      "SalesOtherSku7d": null,
      "SalesSameSku7d": null,
      "Spend": null,
      "UnitsSoldOtherSku7d": null,
      "UnitsSoldSameSku7d": null,
      "accountId": 298,
      "acos_15": null,
      "acos_30": null,
      "acos_7": null,
      "acos_life_time": "1.015368",
      "adGroupId": 333603795971902,
      "adId": 318696217183080,
      "asin": "B0FDQTG22G",
      "campaignId": 300848337365885,
      "campaignName": "auto_safari goodie bag_dh2685",
      "campaignState": 1,
      "created_at": "2025-07-29 15:49:31",
      "dailyBudget": "3.00",
      "groupName": "auto_safari goodie bag_dh2685",
      "groupState": 1,
      "hasPlacement": 0,
      "isPublic": false,
      "keywordPosition": 1,
      "lastAdvUpdatedDate": "2026-03-30 17:45:57",
      "lowCost": 0,
      "manualAdjustTheTime": "2026-03-30 17:45:57",
      "memoKey": null,
      "moduleId": 0,
      "moduleName": "",
      "placementACOSMin": null,
      "positionType": "auto",
      "productLine": {
        "cpc": "0.334297",
        "cps": "13.310257522507769",
        "ctr": "1.27",
        "sku": "DH2685"
      },
      "productVariantInfo": {
        "asin": "B0FDQTG22G",
        "productType": "普通产品",
        "sku": "DH2685",
        "variantData": {
          "ITEM_PACKAGE_QUANTITY": "18 Pcs"
        },
        "variationThemeName": "ITEM_PACKAGE_QUANTITY"
      },
      "proportion": 0,
      "servingStatus": "AD_STATUS_LIVE",
      "servingStatusDetail": "",
      "servingStatusTitle": "ELIGIBLE;",
      "siteId": 4,
      "sku": "DH2685",
      "skuInvData": {
        "asin": "B0FDQTG22G",
        "ful_date": "2025-07-29",
        "graphics_url": "https://m.media-amazon.com/images/I/51N0P931nKL._SL75_.jpg",
        "price": "14.99",
        "sale_status": "正常销售",
        "sales_day": "999 / 119 / 170",
        "servingStatusDetail": "",
        "servingStatusTitle": "ELIGIBLE;",
        "sku": "DH2685",
        "solr_term": "夏季产品(平时可卖)"
      },
      "startDate": "2025-07-29",
      "state": 1,
      "test_module": [],
      "updateWeekday": "否"
    },
    {
      "ACOS": null,
      "CPC": null,
      "CPS": null,
      "CTR": null,
      "Clicks": null,
      "ConversionRate": null,
      "Impressions": null,
      "Orders": null,
      "ROAS": null,
      "SPS": null,
      "Sales": null,
      "SalesOtherSku7d": null,
      "SalesSameSku7d": null,
      "Spend": null,
      "UnitsSoldOtherSku7d": null,
      "UnitsSoldSameSku7d": null,
      "accountId": 515,
      "acos_15": null,
      "acos_30": null,
      "acos_7": null,
      "acos_life_time": "0.211448",
      "adGroupId": 488757766669067,
      "adId": 332414082113810,
      "asin": "B0CBRZJV1V",
      "campaignId": 392909508871585,
      "campaignName": "auto_inspirational pens_uan1383",
      "campaignState": 1,
      "created_at": "2025-11-06 22:32:20",
      "dailyBudget": "3.00",
      "groupName": "auto_inspirational pens_uan1383",
      "groupState": 1,
      "hasPlacement": 0,
      "isPublic": false,
      "keywordPosition": 1,
      "lastAdvUpdatedDate": "2026-03-21 04:36:56",
      "lowCost": 0,
      "manualAdjustTheTime": "2026-03-06 19:42:58",
      "memoKey": null,
      "moduleId": 0,
      "moduleName": "",
      "placementACOSMin": null,
      "positionType": "auto",
      "productLine": {
        "cpc": "0.327097",
        "cps": "13.386794565541953",
        "ctr": "1.27",
        "sku": "UAN1383"
      },
      "productVariantInfo": {
        "asin": "B0CBRZJV1V",
        "productType": "组合变体",
        "sku": "UAN1383",
        "variantData": "",
        "variationThemeName": ""
      },
      "proportion": 0,
      "servingStatus": "AD_STATUS_LIVE",
      "servingStatusDetail": "",
      "servingStatusTitle": "ELIGIBLE;",
      "siteId": 4,
      "sku": "UAN1383",
      "skuInvData": {
        "asin": "B0CBRZJV1V",
        "ful_date": "2023-09-12",
        "graphics_url": "https://m.media-amazon.com/images/I/51TeAFoexuL._SL75_.jpg",
        "price": "28.99",
        "sale_status": "正常销售",
        "sales_day": "999 / 999 / 999",
        "servingStatusDetail": "",
        "servingStatusTitle": "ELIGIBLE;",
        "sku": "UAN1383",
        "solr_term": "母亲节(4-5月)"
      },
      "startDate": "2025-11-06",
      "state": 1,
      "test_module": [],
      "updateWeekday": "否"
    },
    {
      "ACOS": null,
      "CPC": null,
      "CPS": null,
      "CTR": null,
      "Clicks": null,
      "ConversionRate": null,
      "Impressions": null,
      "Orders": null,
      "ROAS": null,
      "SPS": null,
      "Sales": null,
      "SalesOtherSku7d": null,
      "SalesSameSku7d": null,
      "Spend": null,
      "UnitsSoldOtherSku7d": null,
      "UnitsSoldSameSku7d": null,
      "accountId": 705,
      "acos_15": null,
      "acos_30": null,
      "acos_7": null,
      "acos_life_time": null,
      "adGroupId": 312977524975698,
      "adId": 531693674511255,
      "asin": "B0DT3TRCS2",
      "campaignId": 317060601532949,
      "campaignName": "asin_appreciationballpoint_led3945",
      "campaignState": 1,
      "created_at": "2025-04-16 18:42:41",
      "dailyBudget": "3.00",
      "groupName": "asin_appreciationballpoint_led3945",
      "groupState": 1,
      "hasPlacement": 0,
      "isPublic": false,
      "keywordPosition": 1,
      "lastAdvUpdatedDate": "2026-03-25 20:45:57",
      "lowCost": 0,
      "manualAdjustTheTime": "",
      "memoKey": null,
      "moduleId": 0,
      "moduleName": "",
      "placementACOSMin": null,
      "positionType": "keywordTarget",
      "productLine": {
        "cpc": "0.327097",
        "cps": "13.386794565541953",
        "ctr": "1.27",
        "sku": "LED3945"
      },
      "productVariantInfo": {
        "asin": "B0DT3TRCS2",
        "productType": "组合变体",
        "sku": "LED3945",
        "variantData": {
          "NUMBER_OF_ITEMS": "20 Sets"
        },
        "variationThemeName": "NUMBER_OF_ITEMS"
      },
      "proportion": 0,
      "servingStatus": "AD_STATUS_LIVE",
      "servingStatusDetail": "",
      "servingStatusTitle": "ELIGIBLE;",
      "siteId": 4,
      "sku": "LED3945",
      "skuInvData": {
        "asin": "B0DT3TRCS2",
        "ful_date": "2025-04-05",
        "graphics_url": "https://m.media-amazon.com/images/I/51yXD15vlGL._SL75_.jpg",
        "price": "22.99",
        "sale_status": "正常销售",
        "sales_day": "999 / 999 / 1680",
        "servingStatusDetail": "",
        "servingStatusTitle": "ELIGIBLE;",
        "sku": "LED3945",
        "solr_term": "美国教师节(4-5月)"
      },
      "startDate": "2025-04-16",
      "state": 1,
      "test_module": [],
      "updateWeekday": "否"
    },
    {
      "ACOS": null,
      "CPC": null,
      "CPS": null,
      "CTR": null,
      "Clicks": null,
      "ConversionRate": null,
      "Impressions": null,
      "Orders": null,
      "ROAS": null,
      "SPS": null,
      "Sales": null,
      "SalesOtherSku7d": null,
      "SalesSameSku7d": null,
      "Spend": null,
      "UnitsSoldOtherSku7d": null,
      "UnitsSoldSameSku7d": null,
      "accountId": 195,
      "acos_15": null,
      "acos_30": null,
      "acos_7": null,
      "acos_life_time": "0.140193",
      "adGroupId": 79966946165556,
      "adId": 91830186397788,
      "asin": "B0BBKN6VRB",
      "campaignId": 116078586317326,
      "campaignName": "glass bottles with cork ae1181-a ud",
      "campaignState": 1,
      "created_at": "2023-01-06 12:01:12",
      "dailyBudget": "4.00",
      "groupName": "glass bottles with cork ae1181-a ud",
      "groupState": 1,
      "hasPlacement": 1,
      "isPublic": false,
      "keywordPosition": 1,
      "lastAdvUpdatedDate": "2026-02-21 15:46:11",
      "lowCost": 0,
      "manualAdjustTheTime": "2026-02-21 15:46:12",
      "memoKey": null,
      "moduleId": 0,
      "moduleName": "",
      "placementACOSMin": null,
      "positionType": "auto",
      "productLine": {
        "cpc": "0.252160",
        "cps": "23.184191829484902",
        "ctr": "1.65",
        "sku": "AE1181"
      },
      "productVariantInfo": {
        "asin": "B0BBKN6VRB",
        "productType": "普通产品",
        "sku": "AE1181",
        "variantData": {
          "STYLE_NAME": "It's A Girl"
        },
        "variationThemeName": "STYLE_NAME"
      },
      "proportion": 0,
      "servingStatus": "AD_STATUS_LIVE",
      "servingStatusDetail": "",
      "servingStatusTitle": "ELIGIBLE;",
      "siteId": 4,
      "sku": "AE1181",
      "skuInvData": {
        "asin": "B0BBKN6VRB",
        "ful_date": "2022-10-19",
        "graphics_url": "https://m.media-amazon.com/images/I/512tg-aC5uL._SL75_.jpg",
        "price": "37.59",
        "sale_status": "正常销售",
        "sales_day": "105 / 123 / 263",
        "servingStatusDetail": "",
        "servingStatusTitle": "ELIGIBLE;",
        "sku": "AE1181",
        "solr_term": "常规产品"
      },
      "startDate": "2023-01-06",
      "state": 1,
      "test_module": [],
      "updateWeekday": "否"
    },
    {
      "ACOS": null,
      "CPC": null,
      "CPS": null,
      "CTR": null,
      "Clicks": null,
      "ConversionRate": null,
      "Impressions": null,
      "Orders": null,
      "ROAS": null,
      "SPS": null,
      "Sales": null,
      "SalesOtherSku7d": null,
      "SalesSameSku7d": null,
      "Spend": null,
      "UnitsSoldOtherSku7d": null,
      "UnitsSoldSameSku7d": null,
      "accountId": 839,
      "acos_15": null,
      "acos_30": null,
      "acos_7": null,
      "acos_life_time": "0.176340",
      "adGroupId": 529827628762187,
      "adId": 411471136603259,
      "asin": "B0FVFNY5VJ",
      "campaignId": 324989183455801,
      "campaignName": "auto2_letters patches_lic8799",
      "campaignState": 1,
      "created_at": "2025-11-18 18:27:04",
      "dailyBudget": "3.00",
      "groupName": "auto2_letters patches_lic8799",
      "groupState": 1,
      "hasPlacement": 0,
      "isPublic": false,
      "keywordPosition": 0,
      "lastAdvUpdatedDate": "2026-03-15 04:50:51",
      "lowCost": 0,
      "manualAdjustTheTime": "2026-03-09 14:24:52",
      "memoKey": null,
      "moduleId": 0,
      "moduleName": "",
      "placementACOSMin": null,
      "positionType": "auto",
      "productLine": {
        "cpc": "0.248016",
        "cps": "13.583726742571509",
        "ctr": "1.16",
        "sku": "LIC8799"
      },
      "productVariantInfo": {
        "asin": "B0FVFNY5VJ",
        "productType": "变体",
        "sku": "LIC8799",
        "variantData": {
          "COLOR_NAME": "White",
          "SIZE_NAME": "3 Inch",
          "STYLE_NAME": "Classic"
        },
        "variationThemeName": "COLOR_NAME/SIZE_NAME/STYLE_NAME"
      },
      "proportion": 0,
      "servingStatus": "AD_STATUS_LIVE",
      "servingStatusDetail": "",
      "servingStatusTitle": "ELIGIBLE;",
      "siteId": 4,
      "sku": "LIC8799",
      "skuInvData": {
        "asin": "B0FVFNY5VJ",
        "ful_date": "2025-11-04",
        "graphics_url": "https://m.media-amazon.com/images/I/41VNZXWCORL._SL75_.jpg",
        "price": "15.99",
        "sale_status": "正常销售",
        "sales_day": "35 / 37 / 65",
        "servingStatusDetail": "",
        "servingStatusTitle": "ELIGIBLE;",
        "sku": "LIC8799",
        "solr_term": "圣诞节(平时可卖)"
      },
      "startDate": "2025-11-18",
      "state": 1,
      "test_module": [],
      "updateWeekday": "否"
    },
    {
      "ACOS": null,
      "CPC": null,
      "CPS": null,
      "CTR": null,
      "Clicks": null,
      "ConversionRate": null,
      "Impressions": null,
      "Orders": null,
      "ROAS": null,
      "SPS": null,
      "Sales": null,
      "SalesOtherSku7d": null,
      "SalesSameSku7d": null,
      "Spend": null,
      "UnitsSoldOtherSku7d": null,
      "UnitsSoldSameSku7d": null,
      "accountId": 737,
      "acos_15": null,
      "acos_30": null,
      "acos_7": null,
      "acos_life_time": "0.178882",
      "adGroupId": 459435399789172,
      "adId": 412488347805834,
      "asin": "B0BDL42VW7",
      "campaignId": 538274549693124,
      "campaignName": "kw_giant puppy dog_yut2590",
      "campaignState": 1,
      "created_at": "2025-12-18 14:55:00",
      "dailyBudget": "3.00",
      "groupName": "kw_giant puppy dog_yut2590",
      "groupState": 1,
      "hasPlacement": 0,
      "isPublic": false,
      "keywordPosition": 1,
      "lastAdvUpdatedDate": "2026-03-25 23:26:36",
      "lowCost": 0,
      "manualAdjustTheTime": "2026-03-25 23:26:36",
      "memoKey": null,
      "moduleId": 0,
      "moduleName": "",
      "placementACOSMin": null,
      "positionType": "keywordTarget",
      "productLine": {
        "cpc": "0.302672",
        "cps": "18.719885958660015",
        "ctr": "0.93",
        "sku": "YUT2590"
      },
      "productVariantInfo": {
        "asin": "B0BDL42VW7",
        "productType": "普通产品",
        "sku": "YUT2590",
        "variantData": "",
        "variationThemeName": ""
      },
      "proportion": 0,
      "servingStatus": "AD_STATUS_LIVE",
      "servingStatusDetail": "",
      "servingStatusTitle": "ELIGIBLE;",
      "siteId": 4,
      "sku": "YUT2590",
      "skuInvData": {
        "asin": "B0BDL42VW7",
        "ful_date": "2025-11-10",
        "graphics_url": "https://m.media-amazon.com/images/I/51FXcPNN2TL._SL75_.jpg",
        "price": "69.99",
        "sale_status": "正常销售",
        "sales_day": "39 / 23 / 28",
        "servingStatusDetail": "",
        "servingStatusTitle": "ELIGIBLE;",
        "sku": "YUT2590",
        "solr_term": "圣诞节(平时可卖)"
      },
      "startDate": "2025-12-18",
      "state": 1,
      "test_module": [],
      "updateWeekday": "否"
    },
    {
      "ACOS": null,
      "CPC": null,
      "CPS": null,
      "CTR": null,
      "Clicks": null,
      "ConversionRate": null,
      "Impressions": null,
      "Orders": null,
      "ROAS": null,
      "SPS": null,
      "Sales": null,
      "SalesOtherSku7d": null,
      "SalesSameSku7d": null,
      "Spend": null,
      "UnitsSoldOtherSku7d": null,
      "UnitsSoldSameSku7d": null,
      "accountId": 705,
      "acos_15": null,
      "acos_30": null,
      "acos_7": null,
      "acos_life_time": "0.228815",
      "adGroupId": 555764324390883,
      "adId": 504724826730913,
      "asin": "B0DT3TRCS2",
      "campaignId": 345228307015029,
      "campaignName": "asin2_appreciationballpoint_led3945",
      "campaignState": 1,
      "created_at": "2025-04-22 10:25:30",
      "dailyBudget": "15.00",
      "groupName": "asin2_appreciationballpoint_led3945",
      "groupState": 1,
      "hasPlacement": 0,
      "isPublic": false,
      "keywordPosition": 1,
      "lastAdvUpdatedDate": "2026-03-25 20:45:57",
      "lowCost": 0,
      "manualAdjustTheTime": "",
      "memoKey": null,
      "moduleId": 0,
      "moduleName": "",
      "placementACOSMin": null,
      "positionType": "productTarget",
      "productLine": {
        "cpc": "0.327097",
        "cps": "13.386794565541953",
        "ctr": "1.27",
        "sku": "LED3945"
      },
      "productVariantInfo": {
        "asin": "B0DT3TRCS2",
        "productType": "组合变体",
        "sku": "LED3945",
        "variantData": {
          "NUMBER_OF_ITEMS": "20 Sets"
        },
        "variationThemeName": "NUMBER_OF_ITEMS"
      },
      "proportion": 0,
      "servingStatus": "AD_STATUS_LIVE",
      "servingStatusDetail": "",
      "servingStatusTitle": "ELIGIBLE;",
      "siteId": 4,
      "sku": "LED3945",
      "skuInvData": {
        "asin": "B0DT3TRCS2",
        "ful_date": "2025-04-05",
        "graphics_url": "https://m.media-amazon.com/images/I/51yXD15vlGL._SL75_.jpg",
        "price": "22.99",
        "sale_status": "正常销售",
        "sales_day": "999 / 999 / 1680",
        "servingStatusDetail": "",
        "servingStatusTitle": "ELIGIBLE;",
        "sku": "LED3945",
        "solr_term": "美国教师节(4-5月)"
      },
      "startDate": "2025-04-22",
      "state": 1,
      "test_module": [],
      "updateWeekday": "否"
    },
    {
      "ACOS": null,
      "CPC": null,
      "CPS": null,
      "CTR": null,
      "Clicks": null,
      "ConversionRate": null,
      "Impressions": null,
      "Orders": null,
      "ROAS": null,
      "SPS": null,
      "Sales": null,
      "SalesOtherSku7d": null,
      "SalesSameSku7d": null,
      "Spend": null,
      "UnitsSoldOtherSku7d": null,
      "UnitsSoldSameSku7d": null,
      "accountId": 298,
      "acos_15": null,
      "acos_30": null,
      "acos_7": null,
      "acos_life_time": "0.357417",
      "adGroupId": 368446356285646,
      "adId": 507574719819955,
      "asin": "B0FDQTG22G",
      "campaignId": 560878916499350,
      "campaignName": "asin_safari goodie bag_dh2685",
      "campaignState": 1,
      "created_at": "2025-08-04 19:15:19",
      "dailyBudget": "3.00",
      "groupName": "asin_safari goodie bag_dh2685",
      "groupState": 1,
      "hasPlacement": 0,
      "isPublic": false,
      "keywordPosition": 1,
      "lastAdvUpdatedDate": "2026-03-30 17:45:53",
      "lowCost": 0,
      "manualAdjustTheTime": "2026-03-30 17:45:53",
      "memoKey": null,
      "moduleId": 0,
      "moduleName": "",
      "placementACOSMin": null,
      "positionType": "productTarget",
      "productLine": {
        "cpc": "0.334297",
        "cps": "13.310257522507769",
        "ctr": "1.27",
        "sku": "DH2685"
      },
      "productVariantInfo": {
        "asin": "B0FDQTG22G",
        "productType": "普通产品",
        "sku": "DH2685",
        "variantData": {
          "ITEM_PACKAGE_QUANTITY": "18 Pcs"
        },
        "variationThemeName": "ITEM_PACKAGE_QUANTITY"
      },
      "proportion": 0,
      "servingStatus": "AD_STATUS_LIVE",
      "servingStatusDetail": "",
      "servingStatusTitle": "ELIGIBLE;",
      "siteId": 4,
      "sku": "DH2685",
      "skuInvData": {
        "asin": "B0FDQTG22G",
        "ful_date": "2025-07-29",
        "graphics_url": "https://m.media-amazon.com/images/I/51N0P931nKL._SL75_.jpg",
        "price": "14.99",
        "sale_status": "正常销售",
        "sales_day": "999 / 119 / 170",
        "servingStatusDetail": "",
        "servingStatusTitle": "ELIGIBLE;",
        "sku": "DH2685",
        "solr_term": "夏季产品(平时可卖)"
      },
      "startDate": "2025-08-04",
      "state": 1,
      "test_module": [],
      "updateWeekday": "否"
    },
    {
      "ACOS": null,
      "CPC": null,
      "CPS": null,
      "CTR": null,
      "Clicks": null,
      "ConversionRate": null,
      "Impressions": null,
      "Orders": null,
      "ROAS": null,
      "SPS": null,
      "Sales": null,
      "SalesOtherSku7d": null,
      "SalesSameSku7d": null,
      "Spend": null,
      "UnitsSoldOtherSku7d": null,
      "UnitsSoldSameSku7d": null,
      "accountId": 388,
      "acos_15": null,
      "acos_30": null,
      "acos_7": null,
      "acos_life_time": "0.315819",
      "adGroupId": 286868329990864,
      "adId": 395933741515701,
      "asin": "B0F2F7NBYR",
      "campaignId": 497726141851853,
      "campaignName": "auto_blue floralbags_qa3896",
      "campaignState": 1,
      "created_at": "2025-04-30 15:40:01",
      "dailyBudget": "13.00",
      "groupName": "auto_blue floralbags_qa3896",
      "groupState": 1,
      "hasPlacement": 0,
      "isPublic": false,
      "keywordPosition": 1,
      "lastAdvUpdatedDate": "2026-03-30 17:47:09",
      "lowCost": 0,
      "manualAdjustTheTime": "2026-03-30 17:47:09",
      "memoKey": null,
      "moduleId": 0,
      "moduleName": "",
      "placementACOSMin": null,
      "positionType": "auto",
      "productLine": {
        "cpc": "0.312669",
        "cps": "19.369356486210418",
        "ctr": "1.44",
        "sku": "QA3896"
      },
      "productVariantInfo": {
        "asin": "B0F2F7NBYR",
        "productType": "组合产品",
        "sku": "QA3896",
        "variantData": "",
        "variationThemeName": ""
      },
      "proportion": 0,
      "servingStatus": "AD_STATUS_LIVE",
      "servingStatusDetail": "",
      "servingStatusTitle": "ELIGIBLE;",
      "siteId": 4,
      "sku": "QA3896",
      "skuInvData": {
        "asin": "B0F2F7NBYR",
        "ful_date": "2025-04-29",
        "graphics_url": "https://m.media-amazon.com/images/I/51e38f31ewL._SL75_.jpg",
        "price": "29.99",
        "sale_status": "正常销售",
        "sales_day": "999 / 122 / 312",
        "servingStatusDetail": "",
        "servingStatusTitle": "ELIGIBLE;",
        "sku": "QA3896",
        "solr_term": "婚礼季(平时可卖)"
      },
      "startDate": "2025-04-30",
      "state": 1,
      "test_module": [],
      "updateWeekday": "否"
    },
    {
      "ACOS": null,
      "CPC": null,
      "CPS": null,
      "CTR": null,
      "Clicks": null,
      "ConversionRate": null,
      "Impressions": null,
      "Orders": null,
      "ROAS": null,
      "SPS": null,
      "Sales": null,
      "SalesOtherSku7d": null,
      "SalesSameSku7d": null,
      "Spend": null,
      "UnitsSoldOtherSku7d": null,
      "UnitsSoldSameSku7d": null,
      "accountId": 294,
      "acos_15": null,
      "acos_30": null,
      "acos_7": null,
      "acos_life_time": null,
      "adGroupId": 546789717653709,
      "adId": 306386501668319,
      "asin": "B0DW931ZLZ",
      "campaignId": 284834511029071,
      "campaignName": "christian gifts for women-zo0892-system-keyword",
      "campaignState": 1,
      "created_at": "2025-03-18 16:07:31",
      "dailyBudget": "3.00",
      "groupName": "core",
      "groupState": 1,
      "hasPlacement": 0,
      "isPublic": false,
      "keywordPosition": 1,
      "lastAdvUpdatedDate": "2026-03-25 23:26:47",
      "lowCost": 0,
      "manualAdjustTheTime": "2026-04-10 13:02:33",
      "memoKey": null,
      "moduleId": 0,
      "moduleName": "",
      "placementACOSMin": null,
      "positionType": "keywordTarget",
      "productLine": {
        "cpc": "0.294032",
        "cps": "21.127161055505006",
        "ctr": "1.46",
        "sku": "ZO0892"
      },
      "productVariantInfo": {
        "asin": "B0DW931ZLZ",
        "productType": "变体",
        "sku": "ZO0892",
        "variantData": {
          "ITEM_PACKAGE_QUANTITY": "12 Pcs"
        },
        "variationThemeName": "ITEM_PACKAGE_QUANTITY"
      },
      "proportion": 0,
      "servingStatus": "AD_STATUS_LIVE",
      "servingStatusDetail": "",
      "servingStatusTitle": "ELIGIBLE;",
      "siteId": 4,
      "sku": "ZO0892",
      "skuInvData": {
        "asin": "B0DW931ZLZ",
        "ful_date": "2025-03-13",
        "graphics_url": "https://m.media-amazon.com/images/I/51lCqPzan1L._SL75_.jpg",
        "price": "45.99",
        "sale_status": "正常销售",
        "sales_day": "999 / 199 / 365",
        "servingStatusDetail": "",
        "servingStatusTitle": "ELIGIBLE;",
        "sku": "ZO0892",
        "solr_term": "夏季产品(平时可卖)"
      },
      "startDate": "2025-03-18",
      "state": 1,
      "test_module": [],
      "updateWeekday": "否"
    },
    {
      "ACOS": null,
      "CPC": null,
      "CPS": null,
      "CTR": null,
      "Clicks": null,
      "ConversionRate": null,
      "Impressions": null,
      "Orders": null,
      "ROAS": null,
      "SPS": null,
      "Sales": null,
      "SalesOtherSku7d": null,
      "SalesSameSku7d": null,
      "Spend": null,
      "UnitsSoldOtherSku7d": null,
      "UnitsSoldSameSku7d": null,
      "accountId": 639,
      "acos_15": null,
      "acos_30": null,
      "acos_7": null,
      "acos_life_time": "0.215083",
      "adGroupId": 505733559635653,
      "adId": 498256732635639,
      "asin": "B0CJ53ZB7Y",
      "campaignId": 506021562500877,
      "campaignName": "auto_commercial food storage_dun1392",
      "campaignState": 1,
      "created_at": "2025-10-16 15:43:55",
      "dailyBudget": "3.00",
      "groupName": "auto_commercial food storage_dun1392",
      "groupState": 1,
      "hasPlacement": 0,
      "isPublic": false,
      "keywordPosition": 1,
      "lastAdvUpdatedDate": "2026-02-21 15:46:11",
      "lowCost": 0,
      "manualAdjustTheTime": "2026-02-21 15:46:12",
      "memoKey": null,
      "moduleId": 0,
      "moduleName": "",
      "placementACOSMin": null,
      "positionType": "auto",
      "productLine": {
        "cpc": "0.354411",
        "cps": "17.960009114731687",
        "ctr": "1.09",
        "sku": "DUN1392"
      },
      "productVariantInfo": {
        "asin": "B0CJ53ZB7Y",
        "productType": "变体",
        "sku": "DUN1392",
        "variantData": "",
        "variationThemeName": ""
      },
      "proportion": 0,
      "servingStatus": "AD_STATUS_LIVE",
      "servingStatusDetail": "",
      "servingStatusTitle": "ELIGIBLE;",
      "siteId": 4,
      "sku": "DUN1392",
      "skuInvData": {
        "asin": "B0CJ53ZB7Y",
        "ful_date": "2023-11-21",
        "graphics_url": "https://m.media-amazon.com/images/I/31n1M88kncL._SL75_.jpg",
        "price": "59.99",
        "sale_status": "正常销售",
        "sales_day": "999 / 999 / 350",
        "servingStatusDetail": "",
        "servingStatusTitle": "ELIGIBLE;",
        "sku": "DUN1392",
        "solr_term": "常规产品"
      },
      "startDate": "2025-10-16",
      "state": 1,
      "test_module": [],
      "updateWeekday": "否"
    },
    {
      "ACOS": null,
      "CPC": null,
      "CPS": null,
      "CTR": null,
      "Clicks": null,
      "ConversionRate": null,
      "Impressions": null,
      "Orders": null,
      "ROAS": null,
      "SPS": null,
      "Sales": null,
      "SalesOtherSku7d": null,
      "SalesSameSku7d": null,
      "Spend": null,
      "UnitsSoldOtherSku7d": null,
      "UnitsSoldSameSku7d": null,
      "accountId": 174,
      "acos_15": null,
      "acos_30": null,
      "acos_7": null,
      "acos_life_time": "0.205410",
      "adGroupId": 43653321523238,
      "adId": 80631750760676,
      "asin": "B09D773B1T",
      "campaignId": 62802847441863,
      "campaignName": "wooden cutting board do0446-system",
      "campaignState": 1,
      "created_at": "2021-09-17 13:47:21",
      "dailyBudget": "15.00",
      "groupName": "wooden cutting board do0446-system",
      "groupState": 1,
      "hasPlacement": 0,
      "isPublic": false,
      "keywordPosition": 1,
      "lastAdvUpdatedDate": "2026-03-12 04:38:27",
      "lowCost": 0,
      "manualAdjustTheTime": "2026-03-12 04:38:33",
      "memoKey": null,
      "moduleId": 0,
      "moduleName": "",
      "placementACOSMin": null,
      "positionType": "keywordTarget",
      "productLine": {
        "cpc": "0.437273",
        "cps": "16.68193717277487",
        "ctr": "1.17",
        "sku": "DO0446"
      },
      "productVariantInfo": {
        "asin": "B09D773B1T",
        "productType": "普通产品",
        "sku": "DO0446",
        "variantData": {
          "ITEM_PACKAGE_QUANTITY": "11.8 x 6.3 x 0.1 Inch",
          "SIZE_NAME": "6 Pcs"
        },
        "variationThemeName": "ITEM_PACKAGE_QUANTITY/SIZE_NAME"
      },
      "proportion": 0,
      "servingStatus": "AD_STATUS_LIVE",
      "servingStatusDetail": "",
      "servingStatusTitle": "ELIGIBLE;",
      "siteId": 4,
      "sku": "DO0446",
      "skuInvData": {
        "asin": "B09D773B1T",
        "ful_date": "2021-09-17",
        "graphics_url": "https://m.media-amazon.com/images/I/5196hEy6vkL._SL75_.jpg",
        "price": "11.99",
        "sale_status": "正常销售",
        "sales_day": "138 / 92 / 163",
        "servingStatusDetail": "",
        "servingStatusTitle": "ELIGIBLE;",
        "sku": "DO0446",
        "solr_term": "圣诞节(平时可卖)"
      },
      "startDate": "2021-09-17",
      "state": 1,
      "test_module": [],
      "updateWeekday": "否"
    },
    {
      "ACOS": null,
      "CPC": null,
      "CPS": null,
      "CTR": null,
      "Clicks": null,
      "ConversionRate": null,
      "Impressions": null,
      "Orders": null,
      "ROAS": null,
      "SPS": null,
      "Sales": null,
      "SalesOtherSku7d": null,
      "SalesSameSku7d": null,
      "Spend": null,
      "UnitsSoldOtherSku7d": null,
      "UnitsSoldSameSku7d": null,
      "accountId": 333,
      "acos_15": null,
      "acos_30": null,
      "acos_7": null,
      "acos_life_time": "0.061258",
      "adGroupId": 464116936661377,
      "adId": 486304778367208,
      "asin": "B0BYJGTQLJ",
      "campaignId": 517029387792993,
      "campaignName": "asin_easter bunny stuffed_pr2214",
      "campaignState": 1,
      "created_at": "2026-01-04 18:19:01",
      "dailyBudget": "3.00",
      "groupName": "asin_easter bunny stuffed_pr2214",
      "groupState": 1,
      "hasPlacement": 0,
      "isPublic": false,
      "keywordPosition": 1,
      "lastAdvUpdatedDate": "2026-04-08 19:51:39",
      "lowCost": 0,
      "manualAdjustTheTime": "2026-04-08 19:51:40",
      "memoKey": null,
      "moduleId": 0,
      "moduleName": "",
      "placementACOSMin": null,
      "positionType": "productTarget",
      "productLine": {
        "cpc": "0.313969",
        "cps": "16.43551352771211",
        "ctr": "1.03",
        "sku": "PR2214"
      },
      "productVariantInfo": {
        "asin": "B0BYJGTQLJ",
        "productType": "普通产品",
        "sku": "PR2214",
        "variantData": {
          "COLOR": "White, Pink, Lilac, Caramel"
        },
        "variationThemeName": "COLOR"
      },
      "proportion": 0,
      "servingStatus": "AD_STATUS_LIVE",
      "servingStatusDetail": "",
      "servingStatusTitle": "ELIGIBLE;",
      "siteId": 4,
      "sku": "PR2214",
      "skuInvData": {
        "asin": "B0BYJGTQLJ",
        "ful_date": "2023-04-02",
        "graphics_url": "https://m.media-amazon.com/images/I/518iS0qnIYL._SL75_.jpg",
        "price": "28.99",
        "sale_status": "正常销售",
        "sales_day": "89 / 69 / 45",
        "servingStatusDetail": "",
        "servingStatusTitle": "ELIGIBLE;",
        "sku": "PR2214",
        "solr_term": "复活节(平时可卖)"
      },
      "startDate": "2026-01-04",
      "state": 1,
      "test_module": [],
      "updateWeekday": "否"
    }
  ],
  "sbRows": [],
  "review": [
    {
      "sku": "ZO0891",
      "dedupeKey": "SP7::ZO0891::284834511029071::546789717653709",
      "actionSource": [
        "sp_7day_untouched"
      ],
      "source": "sp_7day_untouched",
      "action": {
        "id": "SP7::ZO0891::284834511029071::546789717653709",
        "entityType": "skuCandidate",
        "entityLevel": "skuCandidate",
        "source": "sp_7day_untouched",
        "actionSource": [
          "sp_7day_untouched"
        ],
        "canAutoExecute": false,
        "riskLevel": "manual_review",
        "actionType": "review",
        "reason": "7天未调整候选未映射到SKU画像，进入人工复核",
        "candidateKey": "SP7::ZO0891::284834511029071::546789717653709",
        "campaignId": "284834511029071",
        "adGroupId": "546789717653709",
        "sku": "ZO0891"
      }
    }
  ],
  "skipped": [
    {
      "sku": "TH2843",
      "dedupeKey": "SP7::TH2843::396698961698398::335413796452031",
      "actionSource": [
        "sp_7day_untouched"
      ],
      "source": "sp_7day_untouched",
      "action": {
        "id": "SP7::TH2843::396698961698398::335413796452031",
        "entityType": "adGroup",
        "entityLevel": "adGroup",
        "source": "sp_7day_untouched",
        "actionSource": [
          "sp_7day_untouched"
        ],
        "canAutoExecute": false,
        "riskLevel": "cooldown",
        "actionType": "skip",
        "reason": "7天未调整对象近期已被系统自动调价拦截，进入冷却期，本轮不重复执行",
        "candidateKey": "SP7::TH2843::396698961698398::335413796452031",
        "campaignId": "396698961698398",
        "adGroupId": "335413796452031",
        "sku": "TH2843"
      }
    },
    {
      "sku": "YAN2278",
      "dedupeKey": "4::SP::autoTarget::YAN2278::268439054249692::462820465028833::::427733670869950",
      "actionSource": [
        "sp_7day_untouched"
      ],
      "source": "sp_7day_untouched",
      "action": {
        "entityType": "autoTarget",
        "id": "427733670869950",
        "currentBid": 0.05,
        "source": "sp_7day_untouched",
        "actionSource": [
          "sp_7day_untouched"
        ],
        "adType": "SP",
        "entityLevel": "autoTarget",
        "canAutoExecute": false,
        "riskLevel": "skip",
        "reason": "7澶╂湭璋冩暣鍛戒腑锛屼絾褰撳墠鍑轰环 0.05 宸插埌鏈€灏忓彲瀹夊叏璋冩暣绮惧害锛岃烦杩?",
        "sku": "YAN2278",
        "campaignId": "268439054249692",
        "adGroupId": "462820465028833",
        "keywordId": "",
        "targetId": "427733670869950",
        "candidateKey": "SP7::YAN2278::268439054249692::462820465028833",
        "actionType": "skip",
        "dedupeKey": "4::SP::autoTarget::YAN2278::268439054249692::462820465028833::::427733670869950"
      }
    },
    {
      "sku": "DUN1150",
      "dedupeKey": "4::SP::keyword::DUN1150::43389552451606::93748062162119::58633322166952::",
      "actionSource": [
        "sp_7day_untouched"
      ],
      "source": "sp_7day_untouched",
      "action": {
        "entityType": "keyword",
        "id": "58633322166952",
        "currentBid": 0.3,
        "source": "sp_7day_untouched",
        "actionSource": [
          "sp_7day_untouched"
        ],
        "adType": "SP",
        "entityLevel": "keyword",
        "canAutoExecute": false,
        "riskLevel": "skip",
        "reason": "7day untouched hit, child entity is paused without enough relaunch signal",
        "sku": "DUN1150",
        "campaignId": "43389552451606",
        "adGroupId": "93748062162119",
        "keywordId": "58633322166952",
        "targetId": "",
        "candidateKey": "SP7::DUN1150::43389552451606::93748062162119",
        "actionType": "skip",
        "dedupeKey": "4::SP::keyword::DUN1150::43389552451606::93748062162119::58633322166952::"
      }
    },
    {
      "sku": "ZO0892",
      "dedupeKey": "4::SP::autoTarget::ZO0892::547909368577983::427534554674792::::316661546011554",
      "actionSource": [
        "sp_7day_untouched"
      ],
      "source": "sp_7day_untouched",
      "action": {
        "entityType": "autoTarget",
        "id": "316661546011554",
        "currentBid": 0.31,
        "source": "sp_7day_untouched",
        "actionSource": [
          "sp_7day_untouched"
        ],
        "adType": "SP",
        "entityLevel": "autoTarget",
        "canAutoExecute": false,
        "riskLevel": "skip",
        "reason": "7day untouched hit, child entity is paused without enough relaunch signal",
        "sku": "ZO0892",
        "campaignId": "547909368577983",
        "adGroupId": "427534554674792",
        "keywordId": "",
        "targetId": "316661546011554",
        "candidateKey": "SP7::ZO0892::547909368577983::427534554674792",
        "actionType": "skip",
        "dedupeKey": "4::SP::autoTarget::ZO0892::547909368577983::427534554674792::::316661546011554"
      }
    },
    {
      "sku": "NAY0963",
      "dedupeKey": "4::SP::manualTarget::NAY0963::481583699624095::341551208532334::::347278888366589",
      "actionSource": [
        "sp_7day_untouched"
      ],
      "source": "sp_7day_untouched",
      "action": {
        "entityType": "manualTarget",
        "id": "347278888366589",
        "currentBid": 0.27,
        "source": "sp_7day_untouched",
        "actionSource": [
          "sp_7day_untouched"
        ],
        "adType": "SP",
        "entityLevel": "manualTarget",
        "canAutoExecute": false,
        "riskLevel": "skip",
        "reason": "7day untouched hit, child entity is paused without enough relaunch signal",
        "sku": "NAY0963",
        "campaignId": "481583699624095",
        "adGroupId": "341551208532334",
        "keywordId": "",
        "targetId": "347278888366589",
        "candidateKey": "SP7::NAY0963::481583699624095::341551208532334",
        "actionType": "skip",
        "dedupeKey": "4::SP::manualTarget::NAY0963::481583699624095::341551208532334::::347278888366589"
      }
    },
    {
      "sku": "QA3896",
      "dedupeKey": "4::SP::keyword::QA3896::447627255152480::330045573319481::436968528464583::",
      "actionSource": [
        "sp_7day_untouched"
      ],
      "source": "sp_7day_untouched",
      "action": {
        "entityType": "keyword",
        "id": "436968528464583",
        "currentBid": 0.4,
        "source": "sp_7day_untouched",
        "actionSource": [
          "sp_7day_untouched"
        ],
        "adType": "SP",
        "entityLevel": "keyword",
        "canAutoExecute": false,
        "riskLevel": "skip",
        "reason": "7day untouched hit, child entity is paused without enough relaunch signal",
        "sku": "QA3896",
        "campaignId": "447627255152480",
        "adGroupId": "330045573319481",
        "keywordId": "436968528464583",
        "targetId": "",
        "candidateKey": "SP7::QA3896::447627255152480::330045573319481",
        "actionType": "skip",
        "dedupeKey": "4::SP::keyword::QA3896::447627255152480::330045573319481::436968528464583::"
      }
    },
    {
      "sku": "YAN1353",
      "dedupeKey": "4::SP::keyword::YAN1353::385123769483270::492374673770606::374306493633651::",
      "actionSource": [
        "sp_7day_untouched"
      ],
      "source": "sp_7day_untouched",
      "action": {
        "entityType": "keyword",
        "id": "374306493633651",
        "currentBid": 0.15,
        "source": "sp_7day_untouched",
        "actionSource": [
          "sp_7day_untouched"
        ],
        "adType": "SP",
        "entityLevel": "keyword",
        "canAutoExecute": false,
        "riskLevel": "skip",
        "reason": "7day untouched hit, child entity is paused without enough relaunch signal",
        "sku": "YAN1353",
        "campaignId": "385123769483270",
        "adGroupId": "492374673770606",
        "keywordId": "374306493633651",
        "targetId": "",
        "candidateKey": "SP7::YAN1353::385123769483270::492374673770606",
        "actionType": "skip",
        "dedupeKey": "4::SP::keyword::YAN1353::385123769483270::492374673770606::374306493633651::"
      }
    },
    {
      "sku": "OC1858",
      "dedupeKey": "4::SP::manualTarget::OC1858::465131688062269::557772063447648::::324421431891966",
      "actionSource": [
        "sp_7day_untouched"
      ],
      "source": "sp_7day_untouched",
      "action": {
        "entityType": "manualTarget",
        "id": "324421431891966",
        "currentBid": 0.45,
        "source": "sp_7day_untouched",
        "actionSource": [
          "sp_7day_untouched"
        ],
        "adType": "SP",
        "entityLevel": "manualTarget",
        "canAutoExecute": false,
        "riskLevel": "skip",
        "reason": "7day untouched hit, child entity is paused without enough relaunch signal",
        "sku": "OC1858",
        "campaignId": "465131688062269",
        "adGroupId": "557772063447648",
        "keywordId": "",
        "targetId": "324421431891966",
        "candidateKey": "SP7::OC1858::465131688062269::557772063447648",
        "actionType": "skip",
        "dedupeKey": "4::SP::manualTarget::OC1858::465131688062269::557772063447648::::324421431891966"
      }
    },
    {
      "sku": "YAN0087",
      "dedupeKey": "4::SP::keyword::YAN0087::495673565134857::337378426796062::436160185742767::",
      "actionSource": [
        "sp_7day_untouched"
      ],
      "source": "sp_7day_untouched",
      "action": {
        "entityType": "keyword",
        "id": "436160185742767",
        "currentBid": 0.55,
        "source": "sp_7day_untouched",
        "actionSource": [
          "sp_7day_untouched"
        ],
        "adType": "SP",
        "entityLevel": "keyword",
        "canAutoExecute": false,
        "riskLevel": "skip",
        "reason": "7day untouched hit, child entity is paused without enough relaunch signal",
        "sku": "YAN0087",
        "campaignId": "495673565134857",
        "adGroupId": "337378426796062",
        "keywordId": "436160185742767",
        "targetId": "",
        "candidateKey": "SP7::YAN0087::495673565134857::337378426796062",
        "actionType": "skip",
        "dedupeKey": "4::SP::keyword::YAN0087::495673565134857::337378426796062::436160185742767::"
      }
    },
    {
      "sku": "DH2685",
      "dedupeKey": "4::SP::autoTarget::DH2685::300848337365885::333603795971902::::328664723640871",
      "actionSource": [
        "sp_7day_untouched"
      ],
      "source": "sp_7day_untouched",
      "action": {
        "entityType": "autoTarget",
        "id": "328664723640871",
        "currentBid": 0.45,
        "source": "sp_7day_untouched",
        "actionSource": [
          "sp_7day_untouched"
        ],
        "adType": "SP",
        "entityLevel": "autoTarget",
        "canAutoExecute": false,
        "riskLevel": "skip",
        "reason": "7day untouched hit, child entity is paused without enough relaunch signal",
        "sku": "DH2685",
        "campaignId": "300848337365885",
        "adGroupId": "333603795971902",
        "keywordId": "",
        "targetId": "328664723640871",
        "candidateKey": "SP7::DH2685::300848337365885::333603795971902",
        "actionType": "skip",
        "dedupeKey": "4::SP::autoTarget::DH2685::300848337365885::333603795971902::::328664723640871"
      }
    },
    {
      "sku": "UAN1383",
      "dedupeKey": "4::SP::autoTarget::UAN1383::392909508871585::488757766669067::::447694632531561",
      "actionSource": [
        "sp_7day_untouched"
      ],
      "source": "sp_7day_untouched",
      "action": {
        "entityType": "autoTarget",
        "id": "447694632531561",
        "currentBid": 0.16,
        "source": "sp_7day_untouched",
        "actionSource": [
          "sp_7day_untouched"
        ],
        "adType": "SP",
        "entityLevel": "autoTarget",
        "canAutoExecute": false,
        "riskLevel": "skip",
        "reason": "7day untouched hit, child entity is paused without enough relaunch signal",
        "sku": "UAN1383",
        "campaignId": "392909508871585",
        "adGroupId": "488757766669067",
        "keywordId": "",
        "targetId": "447694632531561",
        "candidateKey": "SP7::UAN1383::392909508871585::488757766669067",
        "actionType": "skip",
        "dedupeKey": "4::SP::autoTarget::UAN1383::392909508871585::488757766669067::::447694632531561"
      }
    },
    {
      "sku": "LED3945",
      "dedupeKey": "4::SP::keyword::LED3945::317060601532949::312977524975698::411033166226098::",
      "actionSource": [
        "sp_7day_untouched"
      ],
      "source": "sp_7day_untouched",
      "action": {
        "entityType": "keyword",
        "id": "411033166226098",
        "currentBid": 0.3,
        "source": "sp_7day_untouched",
        "actionSource": [
          "sp_7day_untouched"
        ],
        "adType": "SP",
        "entityLevel": "keyword",
        "canAutoExecute": false,
        "riskLevel": "skip",
        "reason": "7day untouched hit, child entity is paused without enough relaunch signal",
        "sku": "LED3945",
        "campaignId": "317060601532949",
        "adGroupId": "312977524975698",
        "keywordId": "411033166226098",
        "targetId": "",
        "candidateKey": "SP7::LED3945::317060601532949::312977524975698",
        "actionType": "skip",
        "dedupeKey": "4::SP::keyword::LED3945::317060601532949::312977524975698::411033166226098::"
      }
    },
    {
      "sku": "AE1181",
      "dedupeKey": "4::SP::autoTarget::AE1181::116078586317326::79966946165556::::219614327273934",
      "actionSource": [
        "sp_7day_untouched"
      ],
      "source": "sp_7day_untouched",
      "action": {
        "entityType": "autoTarget",
        "id": "219614327273934",
        "currentBid": 0.1,
        "source": "sp_7day_untouched",
        "actionSource": [
          "sp_7day_untouched"
        ],
        "adType": "SP",
        "entityLevel": "autoTarget",
        "canAutoExecute": false,
        "riskLevel": "skip",
        "reason": "7day untouched hit, child entity is paused without enough relaunch signal",
        "sku": "AE1181",
        "campaignId": "116078586317326",
        "adGroupId": "79966946165556",
        "keywordId": "",
        "targetId": "219614327273934",
        "candidateKey": "SP7::AE1181::116078586317326::79966946165556",
        "actionType": "skip",
        "dedupeKey": "4::SP::autoTarget::AE1181::116078586317326::79966946165556::::219614327273934"
      }
    },
    {
      "sku": "LIC8799",
      "dedupeKey": "4::SP::autoTarget::LIC8799::324989183455801::529827628762187::::487945869002281",
      "actionSource": [
        "sp_7day_untouched"
      ],
      "source": "sp_7day_untouched",
      "action": {
        "entityType": "autoTarget",
        "id": "487945869002281",
        "currentBid": 0.27,
        "source": "sp_7day_untouched",
        "actionSource": [
          "sp_7day_untouched"
        ],
        "adType": "SP",
        "entityLevel": "autoTarget",
        "canAutoExecute": false,
        "riskLevel": "skip",
        "reason": "7day untouched hit, child entity is paused without enough relaunch signal",
        "sku": "LIC8799",
        "campaignId": "324989183455801",
        "adGroupId": "529827628762187",
        "keywordId": "",
        "targetId": "487945869002281",
        "candidateKey": "SP7::LIC8799::324989183455801::529827628762187",
        "actionType": "skip",
        "dedupeKey": "4::SP::autoTarget::LIC8799::324989183455801::529827628762187::::487945869002281"
      }
    },
    {
      "sku": "YUT2590",
      "dedupeKey": "4::SP::keyword::YUT2590::538274549693124::459435399789172::461902146778113::",
      "actionSource": [
        "sp_7day_untouched"
      ],
      "source": "sp_7day_untouched",
      "action": {
        "entityType": "keyword",
        "id": "461902146778113",
        "currentBid": 0.31,
        "source": "sp_7day_untouched",
        "actionSource": [
          "sp_7day_untouched"
        ],
        "adType": "SP",
        "entityLevel": "keyword",
        "canAutoExecute": false,
        "riskLevel": "skip",
        "reason": "7day untouched hit, child entity is paused without enough relaunch signal",
        "sku": "YUT2590",
        "campaignId": "538274549693124",
        "adGroupId": "459435399789172",
        "keywordId": "461902146778113",
        "targetId": "",
        "candidateKey": "SP7::YUT2590::538274549693124::459435399789172",
        "actionType": "skip",
        "dedupeKey": "4::SP::keyword::YUT2590::538274549693124::459435399789172::461902146778113::"
      }
    },
    {
      "sku": "LED3945",
      "dedupeKey": "4::SP::manualTarget::LED3945::345228307015029::555764324390883::::304312347765045",
      "actionSource": [
        "sp_7day_untouched"
      ],
      "source": "sp_7day_untouched",
      "action": {
        "entityType": "manualTarget",
        "id": "304312347765045",
        "currentBid": 0.3,
        "source": "sp_7day_untouched",
        "actionSource": [
          "sp_7day_untouched"
        ],
        "adType": "SP",
        "entityLevel": "manualTarget",
        "canAutoExecute": false,
        "riskLevel": "skip",
        "reason": "7day untouched hit, child entity is paused without enough relaunch signal",
        "sku": "LED3945",
        "campaignId": "345228307015029",
        "adGroupId": "555764324390883",
        "keywordId": "",
        "targetId": "304312347765045",
        "candidateKey": "SP7::LED3945::345228307015029::555764324390883",
        "actionType": "skip",
        "dedupeKey": "4::SP::manualTarget::LED3945::345228307015029::555764324390883::::304312347765045"
      }
    },
    {
      "sku": "DH2685",
      "dedupeKey": "4::SP::manualTarget::DH2685::560878916499350::368446356285646::::440868404469827",
      "actionSource": [
        "sp_7day_untouched"
      ],
      "source": "sp_7day_untouched",
      "action": {
        "entityType": "manualTarget",
        "id": "440868404469827",
        "currentBid": 0.25,
        "source": "sp_7day_untouched",
        "actionSource": [
          "sp_7day_untouched"
        ],
        "adType": "SP",
        "entityLevel": "manualTarget",
        "canAutoExecute": false,
        "riskLevel": "skip",
        "reason": "7day untouched hit, child entity is paused without enough relaunch signal",
        "sku": "DH2685",
        "campaignId": "560878916499350",
        "adGroupId": "368446356285646",
        "keywordId": "",
        "targetId": "440868404469827",
        "candidateKey": "SP7::DH2685::560878916499350::368446356285646",
        "actionType": "skip",
        "dedupeKey": "4::SP::manualTarget::DH2685::560878916499350::368446356285646::::440868404469827"
      }
    },
    {
      "sku": "QA3896",
      "dedupeKey": "4::SP::autoTarget::QA3896::497726141851853::286868329990864::::305293395026688",
      "actionSource": [
        "sp_7day_untouched"
      ],
      "source": "sp_7day_untouched",
      "action": {
        "entityType": "autoTarget",
        "id": "305293395026688",
        "currentBid": 0.2,
        "source": "sp_7day_untouched",
        "actionSource": [
          "sp_7day_untouched"
        ],
        "adType": "SP",
        "entityLevel": "autoTarget",
        "canAutoExecute": false,
        "riskLevel": "skip",
        "reason": "7day untouched hit, child entity is paused without enough relaunch signal",
        "sku": "QA3896",
        "campaignId": "497726141851853",
        "adGroupId": "286868329990864",
        "keywordId": "",
        "targetId": "305293395026688",
        "candidateKey": "SP7::QA3896::497726141851853::286868329990864",
        "actionType": "skip",
        "dedupeKey": "4::SP::autoTarget::QA3896::497726141851853::286868329990864::::305293395026688"
      }
    },
    {
      "sku": "ZO0892",
      "dedupeKey": "4::SP::keyword::ZO0892::284834511029071::546789717653709::490080217848070::",
      "actionSource": [
        "sp_7day_untouched"
      ],
      "source": "sp_7day_untouched",
      "action": {
        "entityType": "keyword",
        "id": "490080217848070",
        "currentBid": 0.45,
        "source": "sp_7day_untouched",
        "actionSource": [
          "sp_7day_untouched"
        ],
        "adType": "SP",
        "entityLevel": "keyword",
        "canAutoExecute": false,
        "riskLevel": "skip",
        "reason": "7day untouched hit, child entity is paused without enough relaunch signal",
        "sku": "ZO0892",
        "campaignId": "284834511029071",
        "adGroupId": "546789717653709",
        "keywordId": "490080217848070",
        "targetId": "",
        "candidateKey": "SP7::ZO0892::284834511029071::546789717653709",
        "actionType": "skip",
        "dedupeKey": "4::SP::keyword::ZO0892::284834511029071::546789717653709::490080217848070::"
      }
    },
    {
      "sku": "DUN1392",
      "dedupeKey": "4::SP::autoTarget::DUN1392::506021562500877::505733559635653::::298081839527895",
      "actionSource": [
        "sp_7day_untouched"
      ],
      "source": "sp_7day_untouched",
      "action": {
        "entityType": "autoTarget",
        "id": "298081839527895",
        "currentBid": 0.3,
        "source": "sp_7day_untouched",
        "actionSource": [
          "sp_7day_untouched"
        ],
        "adType": "SP",
        "entityLevel": "autoTarget",
        "canAutoExecute": false,
        "riskLevel": "skip",
        "reason": "7day untouched hit, child entity is paused without enough relaunch signal",
        "sku": "DUN1392",
        "campaignId": "506021562500877",
        "adGroupId": "505733559635653",
        "keywordId": "",
        "targetId": "298081839527895",
        "candidateKey": "SP7::DUN1392::506021562500877::505733559635653",
        "actionType": "skip",
        "dedupeKey": "4::SP::autoTarget::DUN1392::506021562500877::505733559635653::::298081839527895"
      }
    },
    {
      "sku": "DO0446",
      "dedupeKey": "4::SP::keyword::DO0446::62802847441863::43653321523238::90474399365913::",
      "actionSource": [
        "sp_7day_untouched"
      ],
      "source": "sp_7day_untouched",
      "action": {
        "entityType": "keyword",
        "id": "90474399365913",
        "currentBid": 0.4,
        "source": "sp_7day_untouched",
        "actionSource": [
          "sp_7day_untouched"
        ],
        "adType": "SP",
        "entityLevel": "keyword",
        "canAutoExecute": false,
        "riskLevel": "skip",
        "reason": "7day untouched hit, child entity is paused without enough relaunch signal",
        "sku": "DO0446",
        "campaignId": "62802847441863",
        "adGroupId": "43653321523238",
        "keywordId": "90474399365913",
        "targetId": "",
        "candidateKey": "SP7::DO0446::62802847441863::43653321523238",
        "actionType": "skip",
        "dedupeKey": "4::SP::keyword::DO0446::62802847441863::43653321523238::90474399365913::"
      }
    }
  ]
}